wxmsg/__init__.py
wxmsg/wx.py
WxMessage-1.0.0.dist-info/METADATA
WxMessage-1.0.0.dist-info/WHEEL
WxMessage-1.0.0.dist-info/top_level.txt
WxMessage-1.0.0.dist-info/RECORD
