Metadata-Version: 2.1
Name: WxMessage
Version: 1.0.0
Summary: 一个用于微信发送消息的包
Home-page: https://github.com/bosichong/PrimarySchoolMathematics
Author: inilisefa
Author-email: 2659593323@qq.com
License: UNKNOWN
Platform: UNKNOWN
Classifier: Programming Language :: Python :: 3
Classifier: License :: OSI Approved :: Apache Software License
Classifier: Operating System :: OS Independent
